{
  "project_info": {
    "project_number": "199440111541",
    "project_id": "fontis-dine",
    "storage_bucket": "fontis-dine.firebasestorage.app"
  },
  "client": [
    {
      "client_info": {
        "mobilesdk_app_id": "1:199440111541:android:c5d9977b1d457c14306bfc",
        "android_client_info": {
          "package_name": "com.example.fontis_fine_dine"
        }
      },
      "oauth_client": [],
      "api_key": [
        {
          "current_key": "AIzaSyBzRr4hbxej74dsQiLdIQySMKXaapDLIpg"
        }
      ],
      "services": {
        "appinvite_service": {
          "other_platform_oauth_client": []
        }
      }
    }
  ],
  "configuration_version": "1"
}